bsb_nest/__init__.py
bsb_nest/adapter.py
bsb_nest/cell.py
bsb_nest/connection.py
bsb_nest/device.py
bsb_nest/distributions.py
bsb_nest/exceptions.py
bsb_nest/simulation.py
bsb_nest/devices/__init__.py
bsb_nest/devices/dc_generator.py
bsb_nest/devices/multimeter.py
bsb_nest/devices/poisson_generator.py
bsb_nest/devices/sinusoidal_poisson_generator.py
bsb_nest/devices/spike_recorder.py
bsb_nest-7.2.1.dist-info/entry_points.txt
bsb_nest-7.2.1.dist-info/licenses/LICENSE
bsb_nest-7.2.1.dist-info/WHEEL
bsb_nest-7.2.1.dist-info/METADATA
bsb_nest-7.2.1.dist-info/RECORD
